upgcc/__init__.py
upgcc/cli.py
upgcc/version.py
upgcc-1.0.0.dist-info/METADATA
upgcc-1.0.0.dist-info/WHEEL
upgcc-1.0.0.dist-info/entry_points.txt
upgcc-1.0.0.dist-info/top_level.txt
upgcc-1.0.0.dist-info/RECORD
