Metadata-Version: 2.1
Name: upgcc
Version: 1.0.0
Summary: Install GCC without sudo privilege
Home-page: UNKNOWN
Author: UNKNOWN
Author-email: UNKNOWN
License: UNKNOWN
Platform: UNKNOWN
Requires-Dist: requests
Requires-Dist: termcolor
Requires-Dist: beautifulsoup4
